{
  "HVIGOR_OHOS_PLUGIN": {
    "MODULES": [
      {
        "MODULE_NAME": "1043bfc77febe75fafec0c4309faccf1",
        "API_TYPE": "stageMode"
      }
    ],
    "BUILD_MODE": "debug"
  },
  "HVIGOR": {
    "IS_INCREMENTAL": true,
    "IS_DAEMON": true,
    "IS_PARALLEL": true,
    "IS_HVIGORFILE_TYPE_CHECK": false,
    "TASK_TIME": {
      "1043bfc77febe75fafec0c4309faccf1": {
        "init": 455100,
        "CreateModuleInfo": 1630100,
        "ConfigureCmake": 295600,
        "PreCheckSyscap": 585600,
        "ProcessIntegratedHsp": 1764300,
        "BuildNativeWithCmake": 345400,
        "SyscapTransform": 21647500,
        "ProcessStartupConfig": 4662500,
        "BuildNativeWithNinja": 1053000,
        "GenerateLoaderJson": 20672200,
        "buildHotReloadResource": 316500,
        "BuildJS": 3519700,
        "HotReloadArkTS": 6783943200,
        "PackageHap": 331249600,
        "SignHap": 973940500,
        "CollectDebugSymbol": 3821900,
        "assembleHap": 175800
      },
      "APP": {
        "init": 192800
      }
    },
    "CONFIG_PROPERTIES": {
      "enableSignTask": true,
      "skipNativeIncremental": false,
      "hvigor_keepDependency": true
    },
    "BUILD_ID": "202508102116059320",
    "TOTAL_TIME": 8458247900
  }
}