{
  "HVIGOR_OHOS_PLUGIN": {
    "MODULES": [
      {
        "MODULE_NAME": "1043bfc77febe75fafec0c4309faccf1",
        "API_TYPE": "stageMode"
      }
    ],
    "BUILD_MODE": "debug"
  },
  "HVIGOR": {
    "IS_INCREMENTAL": true,
    "IS_DAEMON": true,
    "IS_PARALLEL": true,
    "IS_HVIGORFILE_TYPE_CHECK": false,
    "TASK_TIME": {
      "1043bfc77febe75fafec0c4309faccf1": {
        "CreateModuleInfo": 1039000,
        "ConfigureCmake": 173700,
        "PreCheckSyscap": 188600,
        "ProcessIntegratedHsp": 1349000,
        "BuildNativeWithCmake": 157800,
        "SyscapTransform": 1523100,
        "ProcessStartupConfig": 3873300,
        "BuildNativeWithNinja": 880600,
        "GenerateLoaderJson": 18433200,
        "buildHotReloadResource": 161400,
        "BuildJS": 2460900,
        "HotReloadArkTS": 6593150900,
        "PackageHap": 68204100,
        "SignHap": 185173000,
        "CollectDebugSymbol": 3706700,
        "assembleHap": 137600
      }
    },
    "CONFIG_PROPERTIES": {
      "enableSignTask": true,
      "skipNativeIncremental": false,
      "hvigor_keepDependency": true
    },
    "TOTAL_TIME": 7144601200,
    "BUILD_ID": "202508062139373710"
  }
}